.gitignore
LICENSE.txt
Makefile
README.md
TODO
pre-commit.sh
setup.cfg
setup.py
plinn/__init__.py
plinn/__main__.py
plinn/__version__.py
plinn/_partition.c
plinn/_partition.pyi
plinn/py.typed
plinn.egg-info/PKG-INFO
plinn.egg-info/SOURCES.txt
plinn.egg-info/dependency_links.txt
plinn.egg-info/top_level.txt